ipr/__init__.py
ipr/annotate.py
ipr/connection.py
ipr/constants.py
ipr/content.spec.json
ipr/inputs.py
ipr/ipr.py
ipr/main.py
ipr/py.typed
ipr/summary.py
ipr/therapeutic_options.py
ipr/types.py
ipr/util.py
tests/__init__.py
tests/constants.py
tests/test_annotate.py
tests/test_connection.py
tests/test_inputs.py
tests/test_ipr.py
tests/test_main.py
tests/test_probe.py
tests/test_summary.py
tests/test_util.py
tests/util.py
ipr-3.13.0.dist-info/LICENSE
ipr-3.13.0.dist-info/METADATA
ipr-3.13.0.dist-info/WHEEL
ipr-3.13.0.dist-info/dependency_links.txt
ipr-3.13.0.dist-info/entry_points.txt
ipr-3.13.0.dist-info/top_level.txt
ipr-3.13.0.dist-info/RECORD
