Metadata-Version: 2.1
Name: ipr
Version: 3.13.0
Author: ipr
Author-email: ipr@bcgsc.ca
Maintainer: ipr
Maintainer-email: ipr@bcgsc.ca
Requires-Python: >=3.7
License-File: LICENSE
Requires-Dist: graphkb >=1.11.0
Requires-Dist: biopython
Requires-Dist: progressbar2
Requires-Dist: pandas >=1.1.0
Requires-Dist: jsonschema
Provides-Extra: deploy
Requires-Dist: twine ; extra == 'deploy'
Requires-Dist: wheel ; extra == 'deploy'
Requires-Dist: m2r ; extra == 'deploy'
Provides-Extra: dev
Requires-Dist: twine ; extra == 'dev'
Requires-Dist: wheel ; extra == 'dev'
Requires-Dist: m2r ; extra == 'dev'
Requires-Dist: pytest ; extra == 'dev'
Requires-Dist: pytest-cov ; extra == 'dev'
Requires-Dist: mkdocs ; extra == 'dev'
Requires-Dist: mkdocs-material ; extra == 'dev'
Requires-Dist: markdown-refdocs ; extra == 'dev'
Requires-Dist: flake8 ; extra == 'dev'
Requires-Dist: black ; extra == 'dev'
Requires-Dist: flake8-annotations ; extra == 'dev'
Requires-Dist: isort ; extra == 'dev'
Requires-Dist: mypy ; extra == 'dev'
Provides-Extra: doc
Requires-Dist: mkdocs ; extra == 'doc'
Requires-Dist: mkdocs-material ; extra == 'doc'
Requires-Dist: markdown-refdocs ; extra == 'doc'
Provides-Extra: test
Requires-Dist: pytest ; extra == 'test'
Requires-Dist: pytest-cov ; extra == 'test'
